waliki/__init__.py
waliki/_markups.py
waliki/acl.py
waliki/admin.py
waliki/context_processors.py
waliki/forms.py
waliki/models.py
waliki/plugins.py
waliki/rst2html5.py
waliki/settings.py
waliki/signals.py
waliki/urls.py
waliki/utils.py
waliki/views.py
waliki/attachments/__init__.py
waliki/attachments/admin.py
waliki/attachments/models.py
waliki/attachments/tests.py
waliki/attachments/urls.py
waliki/attachments/views.py
waliki/attachments/waliki_plugin.py
waliki/attachments/migrations/0001_initial.py
waliki/attachments/migrations/0002_auto_20150328_1558.py
waliki/attachments/migrations/__init__.py
waliki/attachments/templates/waliki/attachments.html
waliki/attachments/templates/waliki/attachments_edit_content.html
waliki/attachments/templates/waliki/attachments_edit_extra_script.html
waliki/directives/__init__.py
waliki/directives/embed.py
waliki/directives/transforms.py
waliki/git/__init__.py
waliki/git/admin.py
waliki/git/models.py
waliki/git/urls.py
waliki/git/views.py
waliki/git/waliki_plugin.py
waliki/git/templates/waliki/diff.html
waliki/git/templates/waliki/history.html
waliki/git/templates/waliki/version.html
waliki/git/templates/waliki/whatchanged.html
waliki/git/templates/waliki/whatchanged_rss.html
waliki/management/__init__.py
waliki/management/commands/__init__.py
waliki/management/commands/moin_migration_cleanup.py
waliki/management/commands/sync_waliki.py
waliki/migrations/0001_initial.py
waliki/migrations/0002_aclrule_apply_to.py
waliki/migrations/0003_auto_20141110_0052.py
waliki/migrations/0004_redirect.py
waliki/migrations/0005_auto_20141124_0020.py
waliki/migrations/0006_auto_20170326_2008.py
waliki/migrations/__init__.py
waliki/pdf/__init__.py
waliki/pdf/models.py
waliki/pdf/tests.py
waliki/pdf/urls.py
waliki/pdf/views.py
waliki/pdf/waliki_plugin.py
waliki/search/__init__.py
waliki/search/search_indexes.py
waliki/search/urls.py
waliki/search/views.py
waliki/search/waliki_plugin.py
waliki-0.8.1.dist-info/DESCRIPTION.rst
waliki-0.8.1.dist-info/METADATA
waliki-0.8.1.dist-info/RECORD
waliki-0.8.1.dist-info/WHEEL
waliki-0.8.1.dist-info/metadata.json
waliki-0.8.1.dist-info/top_level.txt
