Metadata-Version: 2.0
Name: waliki
Version: 0.8.1
Summary: An extensible wiki app for Django with a Git backend
Home-page: https://github.com/mgaitan/waliki
Author: Martín Gaitán
Author-email: gaitan@gmail.com
License: BSD
Keywords: django wiki git waliki restructuredtext markdown
Platform: UNKNOWN
Classifier: Development Status :: 4 - Beta
Classifier: Environment :: Web Environment
Classifier: Framework :: Django
Classifier: Operating System :: OS Independent
Classifier: Intended Audience :: Developers
Classifier: License :: OSI Approved :: BSD License
Classifier: Natural Language :: English
Classifier: Natural Language :: Spanish
Classifier: Framework :: Django
Classifier: Framework :: Django :: 1.8
Classifier: Framework :: Django :: 1.9
Classifier: Framework :: Django :: 1.10
Classifier: Programming Language :: Python :: 2
Classifier: Programming Language :: Python :: 2.7
Classifier: Programming Language :: Python :: 3
Classifier: Programming Language :: Python :: 3.4
Classifier: Programming Language :: Python :: 3.5
Classifier: Programming Language :: Python :: Implementation :: PyPy
Classifier: Topic :: Text Editors :: Documentation
Classifier: Topic :: Documentation
Classifier: Topic :: Documentation :: Sphinx
Classifier: Topic :: Text Processing :: Markup
Classifier: Topic :: Internet :: WWW/HTTP :: Dynamic Content
Requires-Dist: Markups
Requires-Dist: django
Requires-Dist: docutils
Requires-Dist: pyquery
Requires-Dist: rst2html5
Requires-Dist: sh
Provides-Extra: all
Requires-Dist: Whoosh; extra == 'all'
Requires-Dist: django-haystack; extra == 'all'
Requires-Dist: django-sendfile; extra == 'all'
Requires-Dist: hovercraft; extra == 'all'
Requires-Dist: markdown; extra == 'all'
Requires-Dist: micawber; extra == 'all'
Requires-Dist: rst2pdf; extra == 'all'
Provides-Extra: attachments
Requires-Dist: django-sendfile; extra == 'attachments'
Provides-Extra: markdown
Requires-Dist: markdown; extra == 'markdown'
Provides-Extra: pdf
Requires-Dist: rst2pdf; extra == 'pdf'
Provides-Extra: restructuredtext
Requires-Dist: micawber; extra == 'restructuredtext'
Provides-Extra: search
Requires-Dist: Whoosh; extra == 'search'
Requires-Dist: django-haystack; extra == 'search'
Provides-Extra: slides
Requires-Dist: hovercraft; extra == 'slides'
